dcc2/__init__.py
dcc2/dccFn.py
dcc2/parseOmaById.py
dcc2/parseOmaBySpec.py
dcc2/parseOrthoxml.py
dcc2/parseOrthoxmlCustom.py
dcc2/prepareDcc.py
dcc2-0.3.3.dist-info/LICENSE
dcc2-0.3.3.dist-info/METADATA
dcc2-0.3.3.dist-info/WHEEL
dcc2-0.3.3.dist-info/entry_points.txt
dcc2-0.3.3.dist-info/top_level.txt
dcc2-0.3.3.dist-info/RECORD
