Metadata-Version: 2.2
Name: dcc2
Version: 0.3.3
Summary: Dynamic core ortholog compilation tool
Home-page: https://github.com/BIONF/dcc2
Author: Vinh Tran
Author-email: tran@bio.uni-frankfurt.de
License: GPL-3.0
Classifier: Environment :: Console
Classifier: Development Status :: 3 - Alpha
Classifier: Intended Audience :: End Users/Desktop
Classifier: License :: OSI Approved :: GNU General Public License v3 or later (GPLv3+)
Classifier: Natural Language :: English
Classifier: Programming Language :: Python :: 3
Requires-Python: >=3.12.0
License-File: LICENSE
Requires-Dist: biopython
Requires-Dist: bs4
Requires-Dist: omadb
Requires-Dist: pyfaidx
Requires-Dist: tqdm
Requires-Dist: greedyFAS
Requires-Dist: requests
Dynamic: author
Dynamic: author-email
Dynamic: classifier
Dynamic: description
Dynamic: description-content-type
Dynamic: home-page
Dynamic: license
Dynamic: requires-dist
Dynamic: requires-python
Dynamic: summary
